{
    "title": "Average Temperature By City (Line Example)",
    "description": "<p>Average temperature from October 1st through August 29th in:</p><ul><li>New York</li><li>San Francisco</li><li>Austin</li></ul>",
    "dataUrl":  "/assets/temp-example-data.json",
    "visualizationType": "Line",
    "seriesKeys": ["New York", "San Francisco", "Austin"],
    "seriesLabel": "City",
    "dataFormat": {
        "roundTo": -1,
        "commas": false,
        "prefix": "",
        "suffix": "°"
    },
    "padding": {
        "top": 0,
        "left": 80,
        "right": 0,
        "bottom": 80
    },
    "yAxis": {
        "label": "Temperature"
    },
    "xAxis": {
        "label": "Date",
        "dataKey": "date",
        "type": "date",
        "dateFormat": "%Y-%m-%d"
    },
    "legend": {
        "label": "Legend"
    },
    "table": {
        "label": "Table",
        "expanded": false
    }
}